{
  "resourceType": "Bundle",
  "type": "searchset",
  "total": 1,
  "entry": [
    {
      "fullUrl": "urn:uuid:c5df3fed-e69c-499f-bdb8-6fe92a4fd253",
      "search": {
        "mode": "include"
      },
      "resource": {
        "resourceType": "Patient",
        "id": "c5df3fed-e69c-499f-bdb8-6fe92a4fd253",
        "identifier": [
          {
            "system": "https://fhir.nhs.uk/Id/nhs-number",
            "value": "5839945242"
          }
        ],
        "name": [
          {
            "prefix": [
              "MS"
            ],
            "given": [
              "STACEY"
            ],
            "family": "TWITCHETT"
          }
        ],
        "birthDate": "1948-04-30",
        "gender": "female",
        "address": [
          {
            "line": [
              "10 HEATHFIELD",
              "COBHAM",
              "SURREY"
            ],
            "postalCode": "KT11 2QY",
            "text": "10 HEATHFIELD, COBHAM, SURREY, KT11 2QY",
            "type": "both",
            "use": "home"
          }
        ]
      }
    },
    {
      "fullUrl": "urn:uuid:c9e0d6d5-e24d-4d4a-9b1b-47e061273a9c",
      "search": {
        "mode": "include"
      },
      "resource": {
        "resourceType": "PractitionerRole",
        "id": "c9e0d6d5-e24d-4d4a-9b1b-47e061273a9c",
        "organization": {
          "identifier": {
            "system": "https://fhir.nhs.uk/Id/ods-organization-code",
            "value": "A83008"
          }
        }
      }
    },
    {
      "fullUrl": "urn:uuid:a62a5733-1e1e-4b22-a76b-7fa674fd8c46",
      "search": {
        "mode": "include"
      },
      "resource": {
        "resourceType": "MedicationRequest",
        "id": "a62a5733-1e1e-4b22-a76b-7fa674fd8c46",
        "identifier": [
          {
            "system": "https://fhir.nhs.uk/Id/prescription-order-item-number",
            "value": "0206F8EF-0194-49C3-807A-ABE5DF42ADC3"
          }
        ],
        "subject": {
          "reference": "urn:uuid:c5df3fed-e69c-499f-bdb8-6fe92a4fd253"
        },
        "status": "active",
        "statusReason": {
          "coding": [
            {
              "system": "https://fhir.nhs.uk/CodeSystem/medicationrequest-status-reason",
              "code": "0001",
              "display": "Prescribing Error"
            }
          ]
        },
        "intent": "order",
        "requester": {
          "reference": "urn:uuid:c9e0d6d5-e24d-4d4a-9b1b-47e061273a9c"
        },
        "performer": {
          "identifier": [
            {
              "system": "https://fhir.nhs.uk/Id/ods-organization-code",
              "value": "VNFKT"
            }
          ]
        },
        "groupIdentifier": {
          "system": "https://fhir.nhs.uk/Id/prescription-order-number",
          "value": "65C4B1-A83008-AA9C1I"
        },
        "medicationCodeableConcept": {
          "text": "Amoxicillin 250mg capsules"
        },
        "courseOfTherapyType": {
          "coding": [
            {
              "system": "http://terminology.hl7.org/CodeSystem/medicationrequest-course-of-therapy",
              "code": "acute",
              "display": "Short course (acute) therapy"
            }
          ]
        },
        "dispenseRequest": {
          "quantity": {
            "value": 20,
            "unit": "tablet"
          },
          "performer": {
            "identifier": [
              {
                "system": "https://fhir.nhs.uk/Id/ods-organization-code",
                "value": "FA565"
              }
            ]
          },
          "extension": [
            {
              "url": "https://fhir.nhs.uk/StructureDefinition/Extension-DM-PerformerSiteType",
              "valueCoding": {
                "system": "https://fhir.nhs.uk/CodeSystem/dispensing-site-preference",
                "code": "P1",
                "display": "Other (e.g. Community Pharmacy)"
              }
            }
          ]
        },
        "dosageInstruction": [
          {
            "text": "2 times a day for 10 days"
          }
        ],
        "substitution": {
          "allowedBoolean": false
        },
        "extension": [
          {
            "url": "https://fhir.nhs.uk/StructureDefinition/Extension-EPS-DispensingInformation",
            "extension": [
              {
                "url": "dispenseStatus",
                "valueCoding": {
                  "system": "https://fhir.nhs.uk/CodeSystem/medicationdispense-type",
                  "code": "0008",
                  "display": "Item with dispenser"
                }
              }
            ]
          },
          {
            "url": "https://fhir.nhs.uk/StructureDefinition/Extension-PendingCancellation",
            "extension": [
              {
                "url": "lineItemPendingCancellation",
                "valueBoolean": true
              }
            ]
          }
        ]
      }
    },
    {
      "fullUrl": "urn:uuid:6209be50-2d0f-4de9-882f-6933031fe9e1",
      "search": {
        "mode": "include"
      },
      "resource": {
        "resourceType": "MedicationRequest",
        "id": "6209be50-2d0f-4de9-882f-6933031fe9e1",
        "identifier": [
          {
            "system": "https://fhir.nhs.uk/Id/prescription-order-item-number",
            "value": "EE3636D5-E411-4656-A47E-053F0464E7AC"
          }
        ],
        "subject": {
          "reference": "urn:uuid:c5df3fed-e69c-499f-bdb8-6fe92a4fd253"
        },
        "status": "active",
        "statusReason": {
          "coding": [
            {
              "system": "https://fhir.nhs.uk/CodeSystem/medicationrequest-status-reason",
              "code": "0001",
              "display": "Prescribing Error"
            }
          ]
        },
        "intent": "order",
        "requester": {
          "reference": "urn:uuid:c9e0d6d5-e24d-4d4a-9b1b-47e061273a9c"
        },
        "performer": {
          "identifier": [
            {
              "system": "https://fhir.nhs.uk/Id/ods-organization-code",
              "value": "VNFKT"
            }
          ]
        },
        "groupIdentifier": {
          "system": "https://fhir.nhs.uk/Id/prescription-order-number",
          "value": "65C4B1-A83008-AA9C1I"
        },
        "medicationCodeableConcept": {
          "text": "Co-codamol 30mg/500mg tablets"
        },
        "courseOfTherapyType": {
          "coding": [
            {
              "system": "http://terminology.hl7.org/CodeSystem/medicationrequest-course-of-therapy",
              "code": "acute",
              "display": "Short course (acute) therapy"
            }
          ]
        },
        "dispenseRequest": {
          "quantity": {
            "value": 20,
            "unit": "tablet"
          },
          "performer": {
            "identifier": [
              {
                "system": "https://fhir.nhs.uk/Id/ods-organization-code",
                "value": "FA565"
              }
            ]
          },
          "extension": [
            {
              "url": "https://fhir.nhs.uk/StructureDefinition/Extension-DM-PerformerSiteType",
              "valueCoding": {
                "system": "https://fhir.nhs.uk/CodeSystem/dispensing-site-preference",
                "code": "P1",
                "display": "Other (e.g. Community Pharmacy)"
              }
            }
          ]
        },
        "dosageInstruction": [
          {
            "text": "2 times a day for 10 days"
          }
        ],
        "substitution": {
          "allowedBoolean": false
        },
        "extension": [
          {
            "url": "https://fhir.nhs.uk/StructureDefinition/Extension-EPS-DispensingInformation",
            "extension": [
              {
                "url": "dispenseStatus",
                "valueCoding": {
                  "system": "https://fhir.nhs.uk/CodeSystem/medicationdispense-type",
                  "code": "0008",
                  "display": "Item with dispenser"
                }
              }
            ]
          },
          {
            "url": "https://fhir.nhs.uk/StructureDefinition/Extension-PendingCancellation",
            "extension": [
              {
                "url": "lineItemPendingCancellation",
                "valueBoolean": true
              }
            ]
          }
        ]
      }
    },
    {
      "fullUrl": "urn:uuid:6f06e26a-0ae5-47af-b45e-16c1c3dcb9b7",
      "search": {
        "mode": "include"
      },
      "resource": {
        "resourceType": "MedicationRequest",
        "id": "6f06e26a-0ae5-47af-b45e-16c1c3dcb9b7",
        "identifier": [
          {
            "system": "https://fhir.nhs.uk/Id/prescription-order-item-number",
            "value": "3E3D4CCA-DFE1-4D8E-9BC8-6A1F0FA95C86"
          }
        ],
        "subject": {
          "reference": "urn:uuid:c5df3fed-e69c-499f-bdb8-6fe92a4fd253"
        },
        "status": "active",
        "statusReason": {
          "coding": [
            {
              "system": "https://fhir.nhs.uk/CodeSystem/medicationrequest-status-reason",
              "code": "0001",
              "display": "Prescribing Error"
            }
          ]
        },
        "intent": "order",
        "requester": {
          "reference": "urn:uuid:c9e0d6d5-e24d-4d4a-9b1b-47e061273a9c"
        },
        "performer": {
          "identifier": [
            {
              "system": "https://fhir.nhs.uk/Id/ods-organization-code",
              "value": "VNFKT"
            }
          ]
        },
        "groupIdentifier": {
          "system": "https://fhir.nhs.uk/Id/prescription-order-number",
          "value": "65C4B1-A83008-AA9C1I"
        },
        "medicationCodeableConcept": {
          "text": "Pseudoephedrine hydrochloride 60mg tablets"
        },
        "courseOfTherapyType": {
          "coding": [
            {
              "system": "http://terminology.hl7.org/CodeSystem/medicationrequest-course-of-therapy",
              "code": "acute",
              "display": "Short course (acute) therapy"
            }
          ]
        },
        "dispenseRequest": {
          "quantity": {
            "value": 30,
            "unit": "tablet"
          },
          "performer": {
            "identifier": [
              {
                "system": "https://fhir.nhs.uk/Id/ods-organization-code",
                "value": "FA565"
              }
            ]
          },
          "extension": [
            {
              "url": "https://fhir.nhs.uk/StructureDefinition/Extension-DM-PerformerSiteType",
              "valueCoding": {
                "system": "https://fhir.nhs.uk/CodeSystem/dispensing-site-preference",
                "code": "P1",
                "display": "Other (e.g. Community Pharmacy)"
              }
            }
          ]
        },
        "dosageInstruction": [
          {
            "text": "3 times a day for 10 days"
          }
        ],
        "substitution": {
          "allowedBoolean": false
        },
        "extension": [
          {
            "url": "https://fhir.nhs.uk/StructureDefinition/Extension-EPS-DispensingInformation",
            "extension": [
              {
                "url": "dispenseStatus",
                "valueCoding": {
                  "system": "https://fhir.nhs.uk/CodeSystem/medicationdispense-type",
                  "code": "0008",
                  "display": "Item with dispenser"
                }
              }
            ]
          },
          {
            "url": "https://fhir.nhs.uk/StructureDefinition/Extension-PendingCancellation",
            "extension": [
              {
                "url": "lineItemPendingCancellation",
                "valueBoolean": true
              }
            ]
          }
        ]
      }
    },
    {
      "fullUrl": "urn:uuid:ac76f524-a79c-4fcb-80ab-e3d4d1bf3beb",
      "search": {
        "mode": "include"
      },
      "resource": {
        "resourceType": "MedicationRequest",
        "id": "ac76f524-a79c-4fcb-80ab-e3d4d1bf3beb",
        "identifier": [
          {
            "system": "https://fhir.nhs.uk/Id/prescription-order-item-number",
            "value": "44E252BD-2AB3-4AB1-A5A3-879DEA9B25C3"
          }
        ],
        "subject": {
          "reference": "urn:uuid:c5df3fed-e69c-499f-bdb8-6fe92a4fd253"
        },
        "status": "active",
        "statusReason": {
          "coding": [
            {
              "system": "https://fhir.nhs.uk/CodeSystem/medicationrequest-status-reason",
              "code": "0001",
              "display": "Prescribing Error"
            }
          ]
        },
        "intent": "order",
        "requester": {
          "reference": "urn:uuid:c9e0d6d5-e24d-4d4a-9b1b-47e061273a9c"
        },
        "performer": {
          "identifier": [
            {
              "system": "https://fhir.nhs.uk/Id/ods-organization-code",
              "value": "VNFKT"
            }
          ]
        },
        "groupIdentifier": {
          "system": "https://fhir.nhs.uk/Id/prescription-order-number",
          "value": "65C4B1-A83008-AA9C1I"
        },
        "medicationCodeableConcept": {
          "text": "Azithromycin 250mg capsules"
        },
        "courseOfTherapyType": {
          "coding": [
            {
              "system": "http://terminology.hl7.org/CodeSystem/medicationrequest-course-of-therapy",
              "code": "acute",
              "display": "Short course (acute) therapy"
            }
          ]
        },
        "dispenseRequest": {
          "quantity": {
            "value": 30,
            "unit": "tablet"
          },
          "performer": {
            "identifier": [
              {
                "system": "https://fhir.nhs.uk/Id/ods-organization-code",
                "value": "FA565"
              }
            ]
          },
          "extension": [
            {
              "url": "https://fhir.nhs.uk/StructureDefinition/Extension-DM-PerformerSiteType",
              "valueCoding": {
                "system": "https://fhir.nhs.uk/CodeSystem/dispensing-site-preference",
                "code": "P1",
                "display": "Other (e.g. Community Pharmacy)"
              }
            }
          ]
        },
        "dosageInstruction": [
          {
            "text": "3 times a day for 10 days"
          }
        ],
        "substitution": {
          "allowedBoolean": false
        },
        "extension": [
          {
            "url": "https://fhir.nhs.uk/StructureDefinition/Extension-EPS-DispensingInformation",
            "extension": [
              {
                "url": "dispenseStatus",
                "valueCoding": {
                  "system": "https://fhir.nhs.uk/CodeSystem/medicationdispense-type",
                  "code": "0008",
                  "display": "Item with dispenser"
                }
              }
            ]
          },
          {
            "url": "https://fhir.nhs.uk/StructureDefinition/Extension-PendingCancellation",
            "extension": [
              {
                "url": "lineItemPendingCancellation",
                "valueBoolean": true
              }
            ]
          }
        ]
      }
    },
    {
      "fullUrl": "urn:uuid:c590e73a-55d9-44ea-8533-432f8f927ae1",
      "search": {
        "mode": "match"
      },
      "resource": {
        "resourceType": "RequestGroup",
        "id": "c590e73a-55d9-44ea-8533-432f8f927ae1",
        "identifier": [
          {
            "system": "https://fhir.nhs.uk/Id/prescription-order-number",
            "value": "65C4B1-A83008-AA9C1I"
          }
        ],
        "subject": {
          "reference": "urn:uuid:c5df3fed-e69c-499f-bdb8-6fe92a4fd253"
        },
        "status": "active",
        "intent": "order",
        "author": {
          "identifier": {
            "system": "https://fhir.nhs.uk/Id/ods-organization-code",
            "value": "A83008"
          }
        },
        "authoredOn": "2025-04-24T00:00:00.000Z",
        "extension": [
          {
            "url": "https://fhir.nhs.uk/StructureDefinition/Extension-EPS-PrescriptionStatusHistory",
            "extension": [
              {
                "url": "status",
                "valueCoding": {
                  "system": "https://fhir.nhs.uk/CodeSystem/EPS-task-business-status",
                  "code": "0002",
                  "display": "With Dispenser"
                }
              }
            ]
          },
          {
            "url": "https://fhir.nhs.uk/StructureDefinition/Extension-DM-PrescriptionType",
            "valueCoding": {
              "system": "https://fhir.nhs.uk/CodeSystem/prescription-type",
              "code": "0101",
              "display": "Primary Care Prescriber - Medical Prescriber"
            }
          },
          {
            "url": "https://fhir.nhs.uk/StructureDefinition/Extension-PendingCancellation",
            "extension": [
              {
                "url": "prescriptionPendingCancellation",
                "valueBoolean": true
              }
            ]
          },
          {
            "url": "https://fhir.nhs.uk/StructureDefinition/Extension-EPS-PrescriptionStatusHistory",
            "extension": [
              {
                "url": "cancellationReason",
                "valueCoding": {
                  "system": "https://fhir.nhs.uk/CodeSystem/medicationrequest-status-reason",
                  "code": "0001",
                  "display": "Prescribing Error"
                }
              }
            ]
          }
        ],
        "action": [
          {
            "title": "Prescription Line Items(Medications)",
            "timingTiming": {
              "repeat": {
                "frequency": 1,
                "period": 28,
                "periodUnit": "d"
              }
            },
            "action": [
              {
                "resource": {
                  "reference": "urn:uuid:a62a5733-1e1e-4b22-a76b-7fa674fd8c46"
                }
              },
              {
                "resource": {
                  "reference": "urn:uuid:6209be50-2d0f-4de9-882f-6933031fe9e1"
                }
              },
              {
                "resource": {
                  "reference": "urn:uuid:6f06e26a-0ae5-47af-b45e-16c1c3dcb9b7"
                }
              },
              {
                "resource": {
                  "reference": "urn:uuid:ac76f524-a79c-4fcb-80ab-e3d4d1bf3beb"
                }
              }
            ]
          },
          {
            "title": "Prescription status transitions",
            "action": [
              {
                "title": "Prescription upload successful",
                "timingDateTime": "2025-04-24T12:09:53.000Z",
                "code": [
                  {
                    "coding": [
                      {
                        "system": "https://fhir.nhs.uk/CodeSystem/EPS-task-business-status",
                        "code": "0001",
                        "display": "To be Dispensed"
                      }
                    ]
                  }
                ],
                "participant": [
                  {
                    "extension": [
                      {
                        "url": "http://hl7.org/fhir/5.0/StructureDefinition/extension-RequestOrchestration.action.participant.typeReference",
                        "valueReference": {
                          "identifier": {
                            "system": "https://fhir.nhs.uk/Id/ods-organization-code",
                            "value": "A83008"
                          }
                        }
                      }
                    ]
                  }
                ]
              },
              {
                "title": "Release Request successful",
                "timingDateTime": "2025-04-24T12:09:58.000Z",
                "code": [
                  {
                    "coding": [
                      {
                        "system": "https://fhir.nhs.uk/CodeSystem/EPS-task-business-status",
                        "code": "0002",
                        "display": "With Dispenser"
                      }
                    ]
                  }
                ],
                "participant": [
                  {
                    "extension": [
                      {
                        "url": "http://hl7.org/fhir/5.0/StructureDefinition/extension-RequestOrchestration.action.participant.typeReference",
                        "valueReference": {
                          "identifier": {
                            "system": "https://fhir.nhs.uk/Id/ods-organization-code",
                            "value": "VNFKT"
                          }
                        }
                      }
                    ]
                  }
                ]
              },
              {
                "title": "Prescription/item was not cancelled. With dispenser. Marked for cancellation",
                "timingDateTime": "2025-04-24T12:11:13.000Z",
                "code": [
                  {
                    "coding": [
                      {
                        "system": "https://fhir.nhs.uk/CodeSystem/EPS-task-business-status",
                        "code": "0002",
                        "display": "With Dispenser"
                      }
                    ]
                  }
                ],
                "participant": [
                  {
                    "extension": [
                      {
                        "url": "http://hl7.org/fhir/5.0/StructureDefinition/extension-RequestOrchestration.action.participant.typeReference",
                        "valueReference": {
                          "identifier": {
                            "system": "https://fhir.nhs.uk/Id/ods-organization-code",
                            "value": "A83008"
                          }
                        }
                      }
                    ]
                  }
                ]
              },
              {
                "title": "Prescription/item was not cancelled. With dispenser. Marked for cancellation",
                "timingDateTime": "2025-04-24T12:14:37.000Z",
                "code": [
                  {
                    "coding": [
                      {
                        "system": "https://fhir.nhs.uk/CodeSystem/EPS-task-business-status",
                        "code": "0002",
                        "display": "With Dispenser"
                      }
                    ]
                  }
                ],
                "participant": [
                  {
                    "extension": [
                      {
                        "url": "http://hl7.org/fhir/5.0/StructureDefinition/extension-RequestOrchestration.action.participant.typeReference",
                        "valueReference": {
                          "identifier": {
                            "system": "https://fhir.nhs.uk/Id/ods-organization-code",
                            "value": "A83008"
                          }
                        }
                      }
                    ]
                  }
                ]
              },
              {
                "title": "Prescription/item was not cancelled. With dispenser. Marked for cancellation",
                "timingDateTime": "2025-04-24T12:14:46.000Z",
                "code": [
                  {
                    "coding": [
                      {
                        "system": "https://fhir.nhs.uk/CodeSystem/EPS-task-business-status",
                        "code": "0002",
                        "display": "With Dispenser"
                      }
                    ]
                  }
                ],
                "participant": [
                  {
                    "extension": [
                      {
                        "url": "http://hl7.org/fhir/5.0/StructureDefinition/extension-RequestOrchestration.action.participant.typeReference",
                        "valueReference": {
                          "identifier": {
                            "system": "https://fhir.nhs.uk/Id/ods-organization-code",
                            "value": "A83008"
                          }
                        }
                      }
                    ]
                  }
                ]
              },
              {
                "title": "Prescription/item was not cancelled. With dispenser. Marked for cancellation",
                "timingDateTime": "2025-04-24T12:14:57.000Z",
                "code": [
                  {
                    "coding": [
                      {
                        "system": "https://fhir.nhs.uk/CodeSystem/EPS-task-business-status",
                        "code": "0002",
                        "display": "With Dispenser"
                      }
                    ]
                  }
                ],
                "participant": [
                  {
                    "extension": [
                      {
                        "url": "http://hl7.org/fhir/5.0/StructureDefinition/extension-RequestOrchestration.action.participant.typeReference",
                        "valueReference": {
                          "identifier": {
                            "system": "https://fhir.nhs.uk/Id/ods-organization-code",
                            "value": "A83008"
                          }
                        }
                      }
                    ]
                  }
                ]
              }
            ]
          }
        ]
      }
    }
  ]
}
